pysica/COPYRIGHT.py
pysica/__init__.py
pysica/constants.py
pysica/parameters.py
pysica/analysis/__init__.py
pysica/analysis/bivariate.py
pysica/analysis/spectra.py
pysica/analysis/univariate.py
pysica/analysis/univariate_gnuplot.py
pysica/fortran/__init__.py
pysica/functions/__init__.py
pysica/functions/mathematics.py
pysica/functions/optics.py
pysica/functions/pdf.py
pysica/functions/physics.py
pysica/functions/random_pdf.py
pysica/functions/statistics.py
pysica/functions/fortran/__init__.py
pysica/io/__init__.py
pysica/io/io_files.py
pysica/io/io_screen.py
pysica/managers/__init__.py
pysica/managers/data_manager.py
pysica/managers/unit_manager.py
pysica/managers/gnuplot_manager/__init__.py
pysica/managers/gnuplot_manager/classes.py
pysica/managers/gnuplot_manager/demo.py
pysica/managers/gnuplot_manager/errors.py
pysica/managers/gnuplot_manager/functions.py
pysica/managers/gnuplot_manager/funcutils.py
pysica/managers/gnuplot_manager/global_variables.py
pysica/managers/gnuplot_manager/test.py
pysica/managers/io/__init__.py
pysica/managers/io/io_files.py
pysica/managers/io/io_screen.py
pysica/plasma/__init__.py
pysica/plasma/ccpla/__init__.py
pysica/plasma/ccpla/ccpla.py
pysica/plasma/ccpla/ccpla_analysis.py
pysica/plasma/ccpla/ccpla_defaults.py
pysica/plasma/ccpla/ccpla_gui.py
pysica/plasma/ccpla/ccpla_init.py
pysica/plasma/ccpla/ccpla_kernel.py
pysica/plasma/ccpla/ccpla_plot.py
pysica/plasma/ccpla/ccpla_print.py
pysica/plasma/ccpla/discharge/__init__.py
pysica/plasma/ccpla/discharge/moving_particles.py
pysica/plasma/ccpla/discharge/particle_mover.py
pysica/plasma/ccpla/discharge/particles_data_manager.py
pysica/plasma/ccpla/discharge/reactors.py
pysica/plasma/ccpla/discharge/target_particles.py
pysica/plasma/ccpla/discharge/fortran/__init__.py
pysica/plasmapro/__init__.py
pysica/plasmapro/ccpla.py
pysica/plasmapro/ccpla_analysis.py
pysica/plasmapro/ccpla_defaults.py
pysica/plasmapro/ccpla_gui.py
pysica/plasmapro/ccpla_init.py
pysica/plasmapro/ccpla_kernel.py
pysica-0.4.3.dist-info/LICENSE.txt
pysica-0.4.3.dist-info/METADATA
pysica-0.4.3.dist-info/WHEEL
pysica-0.4.3.dist-info/top_level.txt
pysica-0.4.3.dist-info/RECORD
