Metadata-Version: 2.1
Name: pysica
Version: 0.4.3
Summary: PYthon tools for SImulation and CAlculus
Home-page: https://github.com/pietromandracci/pysica
Author: Pietro Mandracci
Author-email: pietro.mandracci.software@gmail.com
Classifier: Programming Language :: Python :: 3
Classifier: License :: OSI Approved :: GNU General Public License v3 or later (GPLv3+)
Classifier: Operating System :: POSIX :: Linux
Requires-Python: >=3
License-File: LICENSE.txt
